PyFrisk/__init__.py
PyFrisk/helper.py
PyFrisk/ip.py
PyFrisk/proxy.py
PyFrisk-0.0.3.dist-info/METADATA
PyFrisk-0.0.3.dist-info/WHEEL
PyFrisk-0.0.3.dist-info/top_level.txt
PyFrisk-0.0.3.dist-info/RECORD
