Metadata-Version: 2.1
Name: PyFrisk
Version: 0.0.3
Summary: This is the simplest module for quick work with proxy.
Home-page: https://github.com/BrightCat14/Pfrisk
Author: akaruineko
Author-email: brightcat1950@gmail.com
Project-URL: GitHub, https://github.com/BrightCat14/Pfrisk
Keywords: proxy ips helping
Classifier: Programming Language :: Python :: 3.11
Classifier: License :: OSI Approved :: MIT License
Classifier: Operating System :: OS Independent
Requires-Python: >=3.6
Requires-Dist: requests
Requires-Dist: lxml
